LICENSE
MANIFEST.in
README.rst
buildout.cfg
develop.cfg
requirements.txt
setup.py
version.txt
bob/__init__.py
bob.db.verafinger.egg-info/PKG-INFO
bob.db.verafinger.egg-info/SOURCES.txt
bob.db.verafinger.egg-info/dependency_links.txt
bob.db.verafinger.egg-info/entry_points.txt
bob.db.verafinger.egg-info/not-zip-safe
bob.db.verafinger.egg-info/requires.txt
bob.db.verafinger.egg-info/top_level.txt
bob/db/__init__.py
bob/db/verafinger/__init__.py
bob/db/verafinger/create.py
bob/db/verafinger/driver.py
bob/db/verafinger/files.txt
bob/db/verafinger/models.py
bob/db/verafinger/pad.py
bob/db/verafinger/query.py
bob/db/verafinger/test.py
doc/bio.rst
doc/conf.py
doc/guide.rst
doc/index.rst
doc/links.rst
doc/pa.rst
doc/py_api.rst
doc/references.rst