Metadata-Version: 1.2
Name: bob.db.verafinger
Version: 2.0.1
Summary: VERA Fingervein Database Access API for Bob
Home-page: https://gitlab.idiap.ch/bob/bob.db.verafinger
Author: Pedro Tome
Author-email: pedro.tome@idiap.ch
Maintainer: Andre Anjos
Maintainer-email: andre.anjos@idiap.ch
License: BSD
Keywords: fingervein recognition,bob,bob.db,VERA,Fingervein
Platform: UNKNOWN
Classifier: Framework :: Bob
Classifier: Development Status :: 4 - Beta
Classifier: Environment :: Console
Classifier: Intended Audience :: Developers
Classifier: Intended Audience :: Education
Classifier: Intended Audience :: Science/Research
Classifier: License :: OSI Approved :: BSD License
Classifier: Natural Language :: English
Classifier: Programming Language :: Python
Classifier: Programming Language :: Python :: 3
Classifier: Topic :: Scientific/Engineering :: Artificial Intelligence
Classifier: Topic :: Database :: Front-Ends
